{
      "cardingoassets910": {
        "id": "910",
        "dance": "white dress",
        "dress": "white dress",
        "image": "ipfs//QmcECFZWebdgd5odbtjGMmLDBGtD3vUx4omaMg7KSXqf8Z",
        "price": "600",
        "location": "perth metro",
        "Artist Name": "shao",
        "name": "cardingoassets",
        "Display Name": "display",
        "Adult Content": "TRUE",
        "Publisher URL": "site.com",
        "Collection Name": "first edition",
        "Long Description": "lorem lorem ipsume lorem lorem ipsume lorem lorem ipsume lorem lorem ipsume lorem lorem ipsume lorem lorem ipsume lorem lorem ipsume",
        "Asset Description": "my awesome"
      }
}
